templated_mail/__init__.py
templated_mail/mail.py
django_templated_mail_2-1.1.2.dist-info/LICENSE
django_templated_mail_2-1.1.2.dist-info/METADATA
django_templated_mail_2-1.1.2.dist-info/WHEEL
django_templated_mail_2-1.1.2.dist-info/top_level.txt
django_templated_mail_2-1.1.2.dist-info/RECORD
