Metadata-Version: 2.1
Name: django-templated-mail-2
Version: 1.1.2
Summary: Send emails using Django template system.
Home-page: https://github.com/mikewolfd/django-templated-mail
Author: Sunscrapers, Mikewolfd
Author-email: info@sunscrapers.com
License: MIT
Classifier: Development Status :: 5 - Production/Stable
Classifier: Framework :: Django :: 1.11
Classifier: Framework :: Django :: 2.0
Classifier: Framework :: Django :: 2.1
Classifier: Intended Audience :: Developers
Classifier: License :: OSI Approved :: MIT License
Classifier: Operating System :: OS Independent
Classifier: Programming Language :: Python
Classifier: Programming Language :: Python :: 2.7
Classifier: Programming Language :: Python :: 3.4
Classifier: Programming Language :: Python :: 3.5
Classifier: Programming Language :: Python :: 3.6
License-File: LICENSE
